README.rst
setup.py
pymongokeyset/__init__.py
pymongokeyset/handlers.py
pymongokeyset/models.py
pymongokeyset/utils.py
pymongokeyset.egg-info/PKG-INFO
pymongokeyset.egg-info/SOURCES.txt
pymongokeyset.egg-info/dependency_links.txt
pymongokeyset.egg-info/top_level.txt