Metadata-Version: 1.1
Name: pymongokeyset
Version: 1.0.0
Summary: offset-free (skip-free) paging for pymongo
Home-page: https://github.com/ocavue/pymongokeyset
Author: ocavue
Author-email: ocavue@gmail.com
License: MIT License
Keywords: keyset,pymongo
Platform: any
Classifier: Development Status :: 3 - Alpha
Classifier: Programming Language :: Python :: 3
